conditional_get/__init__.py
conditional_get/cli.py
conditional_get-0.3.dist-info/LICENSE
conditional_get-0.3.dist-info/METADATA
conditional_get-0.3.dist-info/WHEEL
conditional_get-0.3.dist-info/entry_points.txt
conditional_get-0.3.dist-info/top_level.txt
conditional_get-0.3.dist-info/RECORD
